
{
    "info":{
    "areaName":"亚洲",
    "center":{"lat":30,"lng":100},
    "details":{
        "name":"中国"
    }
},

"curvesData":

[
    [
        {"stroke": [250, 36, 8]},
        {"strokeWidth": 2},
        {"bezier": [1778, 286, 1780, 285, 1780, 284, 1780, 282]}
    ],
    [
        {"stroke": [250, 36, 8]},
        {"strokeWidth": 2},
        {"line": [1778, 277, 1779, 278]},
        {"bezier": [1779, 278, 1780, 276, 1780, 274, 1780, 272]},
        {"bezier": [1780, 272, 1780, 277, 1782, 290, 1778, 295]},
        {"bezier": [1778, 295, 1775, 300, 1766, 299, 1762, 304]},
        {"bezier": [1762, 304, 1759, 309, 1757, 318, 1751, 319]},
        {"bezier": [1751, 319, 1744, 321, 1738, 312, 1732, 310]},
        {"bezier": [1732, 310, 1731, 309, 1732, 308, 1733, 309]}
    ],
    [
        {"stroke": [250, 36, 8]},
        {"strokeWidth": 2},
        {"bezier": [1742, 310, 1742, 309, 1742, 308, 1742, 308]},
        {"bezier": [1742, 308, 1742, 312, 1744, 317, 1744, 321]}
    ],
    [
        {"stroke": [250, 36, 8]},
        {"strokeWidth": 2},
        {"bezier": [1750, 309, 1750, 313, 1749, 317, 1751, 321]}
    ],
    [
        {"stroke": [250, 36, 8]},
        {"strokeWidth": 2},
        {"bezier": [1753, 306, 1753, 308, 1754, 311, 1756, 313]}
    ],
    [
        {"stroke": [250, 36, 8]},
        {"strokeWidth": 2},
        {"bezier": [1772, 282, 1774, 285, 1773, 289, 1777, 291]}
    ],
    [
        {"stroke": [250, 36, 8]},
        {"strokeWidth": 2},
        {"bezier": [1766, 289, 1768, 292, 1769, 298, 1771, 301]}
    ],
    [
        {"stroke": [250, 36, 8]},
        {"strokeWidth": 2},
        {"bezier": [1726, 322, 1726, 322, 1726, 323, 1727, 323]},
        {"bezier": [1727, 323, 1725, 322, 1727, 321, 1725, 321]},
        {"bezier": [1725, 321, 1723, 321, 1722, 325, 1722, 326]},
        {"bezier": [1722, 326, 1721, 331, 1721, 337, 1721, 342]}
    ],
    [
        {"stroke": [250, 36, 8]},
        {"strokeWidth": 2},
        {"bezier": [1730, 370, 1730, 365, 1733, 361, 1733, 356]},
        {"bezier": [1733, 356, 1732, 353, 1732, 346, 1730, 345]}
    ],
    [
        {"stroke": [250, 36, 8]},
        {"strokeWidth": 2},
        {"bezier": [1720, 325, 1720, 326, 1721, 326, 1721, 326]},
        {"bezier": [1721, 326, 1721, 336, 1727, 340, 1730, 349]},
        {"bezier": [1730, 349, 1734, 360, 1730, 367, 1720, 372]}
    ],
    [
        {"stroke": [250, 36, 8]},
        {"strokeWidth": 2},
        {"bezier": [1796, 330, 1796, 327, 1796, 324, 1796, 321]},
        {"bezier": [1796, 321, 1780, 316, 1783, 340, 1780, 348]},
        {"bezier": [1780, 348, 1778, 354, 1774, 356, 1769, 358]},
        {"bezier": [1769, 358, 1766, 359, 1753, 360, 1754, 366]},
        {"bezier": [1754, 366, 1755, 377, 1779, 359, 1783, 357]},
        {"bezier": [1783, 357, 1787, 354, 1790, 350, 1791, 344]},
        {"bezier": [1791, 344, 1792, 339, 1793, 330, 1798, 327]}
    ],
    [
        {"stroke": [250, 36, 8]},
        {"strokeWidth": 2},
        {"bezier": [1670, 357, 1670, 357, 1668, 356, 1667, 354]},
        {"bezier": [1667, 354, 1672, 359, 1672, 363, 1672, 370]}
    ],
    [
        {"stroke": [250, 36, 8]},
        {"strokeWidth": 2},
        {"bezier": [1678, 364, 1678, 373, 1682, 377, 1682, 385]}
    ],
    [
        {"stroke": [250, 36, 8]},
        {"strokeWidth": 2},
        {"bezier": [1666, 358, 1671, 361, 1686, 374, 1688, 381]},
        {"bezier": [1688, 381, 1691, 389, 1683, 404, 1678, 409]},
        {"bezier": [1678, 409, 1678, 409, 1676, 409, 1675, 409]},
        {"bezier": [1675, 409, 1675, 410, 1674, 411, 1674, 412]},
        {"bezier": [1674, 412, 1672, 412, 1673, 413, 1672, 414]}
    ],
    [
        {"stroke": [250, 36, 8]},
        {"strokeWidth": 2},
        {"bezier": [1615, 460, 1612, 457, 1610, 449, 1606, 456]},
        {"bezier": [1606, 456, 1604, 457, 1604, 468, 1604, 471]},
        {"bezier": [1604, 471, 1602, 482, 1617, 482, 1622, 492]},
        {"bezier": [1622, 492, 1625, 498, 1632, 512, 1629, 520]},
        {"bezier": [1629, 520, 1625, 530, 1614, 529, 1607, 534]}
    ],
    [
        {"stroke": [250, 36, 8]},
        {"strokeWidth": 2},
        {"bezier": [1594, 468, 1593, 467, 1594, 464, 1597, 463]}
    ],
    [
        {"stroke": [250, 36, 8]},
        {"strokeWidth": 2},
        {"bezier": [1597, 474, 1597, 472, 1599, 472, 1598, 469]},
        {"bezier": [1598, 469, 1599, 469, 1600, 469, 1601, 469]}
    ],
    [
        {"stroke": [250, 36, 8]},
        {"strokeWidth": 2},
        {"bezier": [1604, 481, 1603, 481, 1602, 481, 1601, 481]}
    ],
    [
        {"stroke": [250, 36, 8]},
        {"strokeWidth": 2},
        {"bezier": [1622, 499, 1622, 498, 1622, 498, 1622, 499]},
        {"bezier": [1622, 499, 1621, 502, 1619, 505, 1619, 508]}
    ],
    [
        {"stroke": [250, 36, 8]},
        {"strokeWidth": 2},
        {"bezier": [1628, 504, 1629, 504, 1629, 504, 1628, 504]},
        {"bezier": [1628, 504, 1622, 506, 1621, 516, 1618, 520]}
    ],
    [
        {"stroke": [250, 36, 8]},
        {"strokeWidth": 2},
        {"bezier": [1630, 508, 1631, 511, 1620, 519, 1618, 523]}
    ],
    [
        {"stroke": [250, 36, 8]},
        {"strokeWidth": 2},
        {"bezier": [1618, 490, 1619, 492, 1615, 500, 1613, 502]}
    ],
    [
        {"stroke": [250, 36, 8]},
        {"strokeWidth": 2},
        {"bezier": [1613, 522, 1614, 521, 1615, 522, 1614, 523]},
        {"bezier": [1614, 523, 1613, 524, 1613, 525, 1613, 527]},
        {"bezier": [1613, 527, 1615, 527, 1615, 529, 1616, 529]}
    ],
    [
        {"stroke": [250, 36, 8]},
        {"strokeWidth": 2},
        {"bezier": [1438, 544, 1436, 544, 1436, 544, 1437, 544]},
        {"bezier": [1437, 544, 1442, 541, 1448, 542, 1452, 539]},
        {"bezier": [1452, 539, 1458, 535, 1456, 531, 1456, 525]},
        {"bezier": [1456, 525, 1454, 514, 1456, 501, 1462, 493]},
        {"bezier": [1462, 493, 1465, 489, 1469, 487, 1474, 485]},
        {"bezier": [1474, 485, 1478, 483, 1486, 484, 1490, 481]},
        {"bezier": [1490, 481, 1498, 475, 1500, 463, 1507, 456]}
    ],
    [
        {"stroke": [250, 36, 8]},
        {"strokeWidth": 2},
        {"bezier": [1450, 523, 1446, 527, 1442, 524, 1441, 520]}
    ],
    [
        {"stroke": [250, 36, 8]},
        {"strokeWidth": 2},
        {"line": [1442, 513, 1443, 513]},
        {"bezier": [1443, 513, 1443, 513, 1442, 512, 1443, 513]},
        {"bezier": [1443, 513, 1445, 515, 1447, 517, 1450, 517]}
    ],
    [
        {"stroke": [250, 36, 8]},
        {"strokeWidth": 2},
        {"bezier": [1445, 496, 1447, 500, 1449, 503, 1453, 505]}
    ],
    [
        {"stroke": [250, 36, 8]},
        {"strokeWidth": 2},
        {"bezier": [1451, 489, 1454, 492, 1452, 496, 1457, 498]}
    ],
    [
        {"stroke": [250, 36, 8]},
        {"strokeWidth": 2},
        {"bezier": [1462, 484, 1461, 485, 1462, 486, 1463, 486]}
    ],
    [
        {"stroke": [250, 36, 8]},
        {"strokeWidth": 2},
        {"bezier": [1498, 453, 1498, 453, 1498, 453, 1499, 454]},
        {"line": [1499, 454, 1499, 452]},
        {"bezier": [1499, 452, 1499, 459, 1495, 468, 1496, 475]}
    ],
    [
        {"stroke": [250, 36, 8]},
        {"strokeWidth": 2},
        {"bezier": [1490, 462, 1494, 466, 1490, 473, 1490, 478]}
    ],
    [
        {"stroke": [250, 36, 8]},
        {"strokeWidth": 2},
        {"bezier": [1487, 466, 1489, 473, 1480, 477, 1481, 484]}
    ],
    [
        {"stroke": [250, 36, 8]},
        {"strokeWidth": 2},
        {"bezier": [1448, 502, 1447, 508, 1449, 524, 1454, 528]}
    ],
    [
        {"stroke": [250, 36, 8]},
        {"strokeWidth": 2},
        {"bezier": [1448, 529, 1448, 531, 1451, 534, 1453, 535]}
    ],
    [
        {"stroke": [250, 36, 8]},
        {"strokeWidth": 2},
        {"bezier": [1478, 478, 1477, 477, 1477, 476, 1475, 477]},
        {"bezier": [1475, 477, 1475, 478, 1475, 481, 1475, 483]}
    ],
    [
        {"stroke": [250, 36, 8]},
        {"strokeWidth": 2},
        {"line": [1205, 364, 1206, 365]},
        {"bezier": [1206, 365, 1208, 361, 1203, 358, 1203, 354]},
        {"bezier": [1203, 354, 1197, 352, 1191, 359, 1186, 360]},
        {"bezier": [1186, 360, 1182, 360, 1178, 359, 1175, 358]},
        {"bezier": [1175, 358, 1171, 358, 1167, 360, 1163, 360]},
        {"bezier": [1163, 360, 1153, 360, 1153, 355, 1153, 346]},
        {"bezier": [1153, 346, 1153, 339, 1151, 332, 1150, 325]},
        {"bezier": [1150, 325, 1159, 323, 1167, 322, 1177, 322]},
        {"bezier": [1177, 322, 1181, 322, 1185, 320, 1189, 319]},
        {"bezier": [1189, 319, 1194, 319, 1195, 321, 1199, 324]},
        {"bezier": [1199, 324, 1209, 332, 1237, 337, 1237, 318]},
        {"bezier": [1237, 318, 1244, 317, 1258, 316, 1264, 320]},
        {"bezier": [1264, 320, 1271, 326, 1272, 338, 1275, 345]},
        {"bezier": [1275, 345, 1279, 354, 1282, 359, 1292, 355]},
        {"bezier": [1292, 355, 1304, 352, 1304, 344, 1299, 334]},
        {"bezier": [1299, 334, 1300, 328, 1288, 324, 1284, 321]},
        {"bezier": [1284, 321, 1280, 318, 1279, 316, 1277, 312]},
        {"bezier": [1277, 312, 1275, 307, 1277, 305, 1277, 300]},
        {"bezier": [1277, 300, 1280, 299, 1285, 301, 1288, 300]},
        {"bezier": [1288, 300, 1292, 298, 1292, 292, 1294, 289]},
        {"bezier": [1294, 289, 1297, 286, 1310, 285, 1315, 287]},
        {"bezier": [1315, 287, 1319, 284, 1329, 286, 1333, 290]},
        {"bezier": [1333, 290, 1335, 289, 1341, 288, 1343, 288]},
        {"bezier": [1343, 288, 1347, 287, 1350, 286, 1354, 285]},
        {"bezier": [1354, 285, 1358, 284, 1363, 285, 1367, 284]},
        {"bezier": [1367, 284, 1370, 283, 1373, 279, 1377, 278]},
        {"bezier": [1377, 278, 1377, 275, 1379, 272, 1379, 269]},
        {"bezier": [1379, 269, 1385, 271, 1404, 271, 1409, 269]},
        {"bezier": [1409, 269, 1413, 267, 1415, 263, 1417, 259]},
        {"bezier": [1417, 259, 1418, 255, 1420, 250, 1421, 246]},
        {"bezier": [1421, 246, 1426, 245, 1431, 247, 1435, 245]},
        {"bezier": [1435, 245, 1439, 242, 1442, 238, 1447, 235]},
        {"bezier": [1447, 235, 1454, 231, 1462, 227, 1472, 229]},
        {"bezier": [1472, 229, 1476, 230, 1479, 233, 1483, 235]},
        {"bezier": [1483, 235, 1487, 237, 1491, 238, 1495, 241]},
        {"bezier": [1495, 241, 1501, 245, 1506, 254, 1514, 255]},
        {"bezier": [1514, 255, 1524, 256, 1535, 255, 1546, 255]},
        {"bezier": [1546, 255, 1550, 255, 1555, 254, 1559, 253]},
        {"bezier": [1559, 253, 1563, 253, 1572, 255, 1575, 253]},
        {"bezier": [1575, 253, 1578, 251, 1577, 247, 1580, 246]},
        {"bezier": [1580, 246, 1582, 245, 1585, 246, 1588, 246]},
        {"bezier": [1588, 246, 1594, 246, 1596, 245, 1601, 241]},
        {"bezier": [1601, 241, 1607, 234, 1609, 227, 1611, 219]},
        {"bezier": [1611, 219, 1610, 218, 1609, 217, 1607, 217]},
        {"bezier": [1607, 217, 1607, 211, 1616, 208, 1621, 208]},
        {"bezier": [1621, 208, 1627, 209, 1633, 212, 1639, 206]},
        {"bezier": [1639, 206, 1643, 205, 1651, 205, 1657, 205]},
        {"bezier": [1657, 205, 1665, 206, 1668, 209, 1674, 215]},
        {"bezier": [1674, 215, 1679, 218, 1683, 222, 1688, 223]},
        {"bezier": [1688, 223, 1693, 223, 1694, 223, 1697, 220]},
        {"bezier": [1697, 220, 1699, 220, 1704, 215, 1705, 214]},
        {"bezier": [1705, 214, 1710, 213, 1713, 223, 1716, 226]},
        {"bezier": [1716, 226, 1722, 231, 1730, 231, 1738, 232]},
        {"bezier": [1738, 232, 1744, 233, 1747, 235, 1753, 238]},
        {"bezier": [1753, 238, 1758, 241, 1766, 239, 1772, 238]},
        {"bezier": [1772, 238, 1771, 242, 1773, 245, 1774, 249]},
        {"bezier": [1774, 249, 1774, 253, 1773, 255, 1775, 259]},
        {"bezier": [1775, 259, 1777, 261, 1782, 263, 1783, 265]},
        {"bezier": [1783, 265, 1783, 266, 1778, 274, 1778, 275]},
        {"bezier": [1778, 275, 1771, 286, 1762, 297, 1755, 305]},
        {"bezier": [1755, 305, 1748, 307, 1739, 302, 1733, 304]},
        {"bezier": [1733, 304, 1732, 308, 1729, 317, 1726, 320]},
        {"bezier": [1726, 320, 1723, 323, 1715, 323, 1715, 330]},
        {"bezier": [1715, 330, 1715, 333, 1721, 341, 1723, 344]},
        {"bezier": [1723, 344, 1727, 351, 1728, 355, 1724, 363]},
        {"bezier": [1724, 363, 1718, 377, 1709, 353, 1707, 346]},
        {"bezier": [1707, 346, 1706, 342, 1705, 335, 1700, 333]},
        {"bezier": [1700, 333, 1694, 330, 1687, 334, 1685, 340]},
        {"bezier": [1685, 340, 1675, 341, 1673, 337, 1667, 330]},
        {"bezier": [1667, 330, 1662, 332, 1656, 334, 1655, 340]},
        {"bezier": [1655, 340, 1654, 340, 1653, 340, 1652, 340]},
        {"bezier": [1652, 340, 1649, 348, 1664, 350, 1668, 352]},
        {"bezier": [1668, 352, 1665, 358, 1662, 359, 1663, 367]},
        {"bezier": [1663, 367, 1674, 367, 1674, 378, 1678, 385]},
        {"bezier": [1678, 385, 1683, 395, 1682, 399, 1676, 409]},
        {"bezier": [1676, 409, 1671, 416, 1666, 422, 1661, 429]},
        {"bezier": [1661, 429, 1659, 432, 1658, 435, 1655, 438]},
        {"bezier": [1655, 438, 1654, 441, 1649, 445, 1649, 448]},
        {"bezier": [1649, 448, 1641, 448, 1633, 453, 1627, 457]},
        {"bezier": [1627, 457, 1620, 461, 1607, 462, 1605, 451]},
        {"bezier": [1605, 451, 1604, 451, 1601, 451, 1600, 451]},
        {"bezier": [1600, 451, 1599, 460, 1586, 469, 1595, 478]},
        {"bezier": [1595, 478, 1600, 484, 1608, 485, 1611, 493]},
        {"bezier": [1611, 493, 1614, 500, 1620, 513, 1616, 521]},
        {"bezier": [1616, 521, 1615, 523, 1611, 526, 1609, 528]},
        {"bezier": [1609, 528, 1606, 531, 1604, 535, 1601, 537]},
        {"bezier": [1601, 537, 1599, 537, 1597, 536, 1595, 536]},
        {"bezier": [1595, 536, 1595, 536, 1595, 535, 1595, 534]},
        {"bezier": [1595, 534, 1590, 533, 1588, 529, 1583, 527]},
        {"bezier": [1583, 527, 1580, 526, 1574, 526, 1571, 523]},
        {"bezier": [1571, 523, 1568, 519, 1571, 515, 1569, 511]},
        {"bezier": [1569, 511, 1567, 506, 1563, 508, 1559, 506]},
        {"bezier": [1559, 506, 1559, 511, 1559, 516, 1559, 521]},
        {"bezier": [1559, 521, 1554, 517, 1552, 514, 1549, 510]},
        {"bezier": [1549, 510, 1547, 507, 1546, 506, 1544, 504]},
        {"bezier": [1544, 504, 1541, 502, 1540, 502, 1537, 501]},
        {"bezier": [1537, 501, 1533, 499, 1533, 500, 1532, 496]},
        {"bezier": [1532, 496, 1532, 494, 1530, 489, 1530, 487]},
        {"bezier": [1530, 487, 1530, 485, 1531, 483, 1531, 481]},
        {"bezier": [1531, 481, 1530, 478, 1528, 476, 1529, 472]},
        {"bezier": [1529, 472, 1515, 471, 1523, 448, 1527, 442]},
        {"bezier": [1527, 442, 1526, 446, 1522, 461, 1517, 462]},
        {"bezier": [1517, 462, 1510, 463, 1511, 451, 1504, 451]},
        {"bezier": [1504, 451, 1496, 452, 1493, 461, 1490, 466]},
        {"bezier": [1490, 466, 1485, 473, 1477, 470, 1471, 475]},
        {"bezier": [1471, 475, 1465, 479, 1461, 486, 1456, 490]},
        {"bezier": [1456, 490, 1453, 492, 1450, 494, 1448, 496]},
        {"bezier": [1448, 496, 1444, 500, 1445, 503, 1445, 508]},
        {"bezier": [1445, 508, 1445, 516, 1446, 526, 1444, 534]},
        {"bezier": [1444, 534, 1441, 540, 1436, 544, 1432, 549]},
        {"bezier": [1432, 549, 1426, 540, 1426, 530, 1419, 520]},
        {"bezier": [1419, 520, 1416, 516, 1415, 512, 1414, 507]},
        {"bezier": [1414, 507, 1413, 503, 1413, 502, 1412, 499]},
        {"bezier": [1412, 499, 1410, 496, 1408, 494, 1409, 490]},
        {"bezier": [1409, 490, 1396, 487, 1400, 471, 1400, 461]},
        {"bezier": [1400, 461, 1399, 463, 1398, 465, 1396, 466]},
        {"bezier": [1396, 466, 1389, 459, 1388, 454, 1386, 444]},
        {"bezier": [1386, 444, 1380, 445, 1368, 440, 1367, 433]},
        {"bezier": [1367, 433, 1356, 432, 1348, 438, 1337, 438]},
        {"bezier": [1337, 438, 1330, 437, 1318, 433, 1316, 424]},
        {"bezier": [1316, 424, 1305, 423, 1299, 425, 1290, 419]},
        {"bezier": [1290, 419, 1285, 415, 1274, 408, 1272, 402]},
        {"bezier": [1272, 402, 1270, 405, 1268, 407, 1266, 409]},
        {"bezier": [1266, 409, 1268, 414, 1268, 418, 1273, 422]},
        {"bezier": [1273, 422, 1277, 427, 1280, 431, 1283, 436]},
        {"bezier": [1283, 436, 1286, 441, 1290, 446, 1296, 447]},
        {"bezier": [1296, 447, 1300, 448, 1301, 448, 1304, 444]},
        {"bezier": [1304, 444, 1305, 441, 1307, 437, 1307, 433]},
        {"bezier": [1307, 433, 1313, 435, 1315, 441, 1320, 444]},
        {"bezier": [1320, 444, 1326, 448, 1335, 447, 1334, 457]},
        {"bezier": [1334, 457, 1334, 462, 1329, 469, 1325, 473]},
        {"bezier": [1325, 473, 1324, 475, 1321, 477, 1319, 479]},
        {"bezier": [1319, 479, 1317, 481, 1315, 483, 1313, 485]},
        {"bezier": [1313, 485, 1307, 490, 1298, 486, 1291, 487]},
        {"bezier": [1291, 487, 1284, 488, 1280, 494, 1277, 499]},
        {"bezier": [1277, 499, 1273, 504, 1271, 509, 1265, 513]},
        {"bezier": [1265, 513, 1263, 515, 1260, 516, 1256, 517]},
        {"bezier": [1256, 517, 1253, 518, 1249, 518, 1246, 520]},
        {"bezier": [1246, 520, 1245, 513, 1247, 506, 1244, 499]},
        {"bezier": [1244, 499, 1241, 494, 1235, 492, 1232, 487]},
        {"bezier": [1232, 487, 1228, 482, 1225, 474, 1225, 469]},
        {"bezier": [1225, 469, 1224, 464, 1224, 464, 1222, 460]},
        {"bezier": [1222, 460, 1221, 457, 1218, 455, 1217, 453]},
        {"bezier": [1217, 453, 1213, 447, 1212, 440, 1208, 435]},
        {"bezier": [1208, 435, 1204, 430, 1200, 426, 1197, 420]},
        {"bezier": [1197, 420, 1196, 418, 1194, 412, 1192, 410]},
        {"bezier": [1192, 410, 1188, 408, 1185, 411, 1182, 410]},
        {"bezier": [1182, 410, 1177, 410, 1171, 402, 1169, 397]},
        {"bezier": [1169, 397, 1177, 392, 1191, 383, 1201, 389]},
        {"bezier": [1201, 389, 1208, 387, 1208, 366, 1210, 367]},
        {"line": [1210, 367, 1270, 399]},
        {"bezier": [1270, 399, 1270, 399, 1271, 400, 1271, 399]},
        {"bezier": [1271, 399, 1270, 404, 1275, 417, 1279, 420]},
        {"line": [1279, 420, 1279, 411]},
        {"bezier": [1279, 411, 1282, 414, 1286, 420, 1288, 425]},
        {"bezier": [1288, 425, 1289, 426, 1290, 426, 1291, 426]},
        {"line": [1291, 426, 1294, 417]},
        {"bezier": [1294, 417, 1295, 419, 1297, 422, 1300, 424]},
        {"line": [1300, 424, 1304, 424]},
        {"line": [1304, 424, 1304, 423]},
        {"line": [1304, 423, 1304, 430]},
        {"bezier": [1304, 430, 1298, 429, 1291, 428, 1285, 425]},
        {"bezier": [1285, 425, 1281, 424, 1269, 418, 1270, 414]},
        {"line": [1270, 414, 1372, 439]},
        {"bezier": [1372, 439, 1367, 440, 1365, 435, 1364, 432]},
        {"bezier": [1364, 432, 1361, 432, 1355, 433, 1352, 435]},
        {"bezier": [1352, 435, 1349, 436, 1346, 439, 1343, 436]},
        {"bezier": [1343, 436, 1342, 443, 1332, 443, 1330, 438]},
        {"bezier": [1330, 438, 1331, 439, 1334, 441, 1334, 441]},
        {"line": [1334, 441, 1327, 442]},
        {"bezier": [1327, 442, 1329, 450, 1346, 443, 1350, 442]},
        {"bezier": [1350, 442, 1355, 441, 1358, 440, 1363, 442]},
        {"bezier": [1363, 442, 1367, 444, 1370, 447, 1375, 447]},
        {"bezier": [1375, 447, 1376, 447, 1376, 447, 1375, 447]}
    ]
]

}
